{
	"information": {
		"id_generator": {
			"user_id": 4,
			"purchase_id": 4,
			"product_id": 0
		}
	},
	"users": [
		{
			"id": 1,
			"name": "bolodoido",
			"email": "client_5@gmail.com",
			"phone": "(19) 99999-9999",
			"cpf": "99990555599"
		},
		{
			"id": 2,
			"name": "client_2",
			"email": "client_2@gmail.com",
			"phone": "(19) 99999-9999",
			"cpf": "99990555599"
		},
		{
			"id": 3,
			"name": "double barrel",
			"email": "client_4@gmail.com",
			"phone": "(19) 99999-9999",
			"cpf": "99990555599"
		},
		{
			"id": 4,
			"name": "bolodoido",
			"email": "client_5555@gmail.com",
			"phone": "(19) 99999-9999",
			"cpf": "99990555599"
		}
	],
	"purchases": [
		{
			"purchase_id": 1,
			"user_id": 2,
			"products": [
				{
					"product_id": 5,
					"name": "product_05",
					"cost": 1000,
					"quantity": 1
				}
			]
		},
		{
			"purchase_id": 2,
			"user_id": 2,
			"products": [
				{
					"product_id": 2,
					"name": "product_01",
					"cost": 200,
					"quantity": 10
				}
			]
		},
		{
			"purchase_id": 3,
			"user_id": 1,
			"products": [
				{
					"product_id": 2,
					"name": "product_02",
					"cost": 200,
					"quantity": 10
				},
				{
					"product_id": 1,
					"name": "product_01",
					"cost": 500,
					"quantity": 10
				}
			]
		},
		{
			"purchase_id": 4,
			"user_id": 1,
			"products": [
				{
					"product_id": 3,
					"name": "product_03",
					"cost": 1000,
					"quantity": 1
				}
			]
		}
	],
	"products": [
		{
			"product_id": 1,
			"name": "product_01",
			"cost": 100,
			"total": 99,
			"in_stock": true
		},
		{
			"product_id": 2,
			"name": "product_02",
			"cost": 200,
			"total": 0,
			"in_stock": false
		}
	]
}